rgoogle/__init__.py
rgoogle/esa/__init__.py
rgoogle/esa/__main__.py
rgoogle/esa/cipher.py
rgoogle/esa/keys.py
rgoogle/smali/__init__.py
rgoogle/smali/base.py
rgoogle/smali/opcode.py
rgoogle/smali/reader.py
rgoogle/smali/visitor.py
rgoogle/smali/writer.py
rgoogle/smali/bridge/__init__.py
rgoogle/smali/bridge/vm.py
rgoogle-0.0.1.dist-info/LICENSE
rgoogle-0.0.1.dist-info/METADATA
rgoogle-0.0.1.dist-info/WHEEL
rgoogle-0.0.1.dist-info/top_level.txt
rgoogle-0.0.1.dist-info/RECORD
