Metadata-Version: 2.1
Name: rgoogle
Version: 0.0.1
Summary: Smali Visitor-API and Decryptor for Google's hidden JAR files
Author-email: MatrixEditor <not@supported.com>
Project-URL: Homepage, https://github.com/MatrixEditor/roogle
Project-URL: API-Docs, https://rgoogle.readthedocs.io/rgoogle
Classifier: Development Status :: 5 - Production/Stable
Classifier: Intended Audience :: Science/Research
Classifier: License :: OSI Approved :: MIT License
Classifier: Programming Language :: Python :: 3.6
Classifier: Programming Language :: Python :: 3.7
Classifier: Programming Language :: Python :: 3.8
Classifier: Programming Language :: Python :: 3.9
Classifier: Programming Language :: Python :: 3.10
License-File: LICENSE
